{
    "name_ru": "Сотворение пламени",
    "name": "Produce flame",
    "components": {
        "verbal": true,
        "somatic": true,
        "material": false
    },
    "material_component": "В,",
    "casting_time": 4,
    "description": "В вашей ладони появляется мерцающее пламя. Оно остаётся там, пока заклинание активно, и не вредит ни вам, ни вашему снаряжению. Огонь испускает яркий свет в радиусе 10 футов и тусклый свет в пределах ещё 10 футов. Заклинание оканчивается, если вы оканчиваете его действием или накладываете ещё раз.
Вы можете атаковать этим пламенем, но это тоже оканчивает заклинание. Когда вы накладываете это заклинание, или другим действием в одном из последующих ходов вы можете метнуть пламя в существо, находящееся в пределах 30 футов от вас. Совершите дальнобойную атаку заклинанием. При попадании цель получает урон огнём 1к8.
Урон этого заклинания увеличивается на 1к8, когда вы достигаете 5-го уровня (2к8), 11-го уровня (3к8) и 17-го уровня (4к8).
",
    "distance": 0,
    "duration": 600,
    "level": "Заговор",
    "is_ritual": false,
    "requires_concentration": false
}