{
    "name_ru": "Притворство",
    "name": "Seeming",
    "components": {
        "verbal": true,
        "somatic": true,
        "material": false
    },
    "material_component": "В,",
    "casting_time": 4,
    "description": "Это заклинание позволяет вам менять облик любого количества существ, видимых вами в пределах дистанции. Вы даёте каждой выбранной цели новый, иллюзорный облик. Несогласная цель может совершить спасбросок Харизмы, и в случае успеха заклинание на неё не действует.
Это заклинание маскирует внешний облик, а также одежду, доспехи, оружие и снаряжение. Вы можете сделать каждое существо на 1 фут (30 сантиметров) ниже или выше, и сделать его худого, толстого или обычного сложения. Вы не можете менять вид тела цели, так что у неё должен быть такой же набор конечностей. Во всём остальном иллюзию определяете вы. Заклинание действует всю свою длительность, но вы можете действием окончить действие заклинания досрочно.
Изменения, внесённые этим заклинанием, не проходят проверку физическим исследованием. Например, если заклинание добавит шляпу к снаряжению персонажа, предметы будут проходить сквозь неё, и все, кто коснутся её, либо не почувствуют ничего, либо почувствуют голову и волосы. Если вы сделаете себя более худым, то рука того, кто захочет к вам прикоснуться, ударится о вас, не дойдя до видимых очертаний.
Существо может действием осмотреть цель и совершить проверку Интеллекта (Расследование) против Сл ваших заклинаний. В случае успеха оно поймёт, что облик ненатурален.
",
    "distance": 30,
    "duration": 28800,
    "level": "5",
    "is_ritual": false,
    "requires_concentration": false
}