{
    "name_ru": "Удар Зефира",
    "name": "Zephyr strike",
    "components": {
        "verbal": true,
        "somatic": false,
        "material": false
    },
    "material_component": "",
    "casting_time": 2,
    "description": "Вы движетесь подобно ветру. Пока действует заклинание, ваше движение не вызывает провоцированных атак.
Единожды до окончания действия заклинания вы можете получить преимущество на одну атаку оружием в свой ход. Эта атака наносит дополнительно 1к8 урона силовым полем при попадании. Вне зависимости от того, попали вы или промахнулись, ваша скорость ходьбы увеличивается на 30 футов до конца этого хода.
",
    "distance": 0,
    "duration": 60,
    "level": "1",
    "is_ritual": false,
    "requires_concentration": true,
    "classes": [
        "ranger"
    ],
    "classes_tce": [],
    "archetypes": []
}